Shelegia_Motta_2021/IModel.py
Shelegia_Motta_2021/Models.py
Shelegia_Motta_2021/__init__.py
shelegia_motta_2021-1.0.4.dist-info/licenses/LICENSE
shelegia_motta_2021-1.0.4.dist-info/METADATA
shelegia_motta_2021-1.0.4.dist-info/WHEEL
shelegia_motta_2021-1.0.4.dist-info/top_level.txt
shelegia_motta_2021-1.0.4.dist-info/RECORD
