Metadata-Version: 2.4
Name: Shelegia_Motta_2021
Version: 1.0.4
Summary: Implements the model presented in Shelegia and Motta (2021)
Home-page: https://github.com/manuelbieri/shelegia_motta_2021
Download-URL: https://github.com/manuelbieri/Shelegia_Motta_2021/archive/refs/tags/v1.0.4.tar.gz
Author: Manuel Bieri
Author-email: mail@manuelbieri.ch
License: MIT
Keywords: Acquisition,Kill Zone
Classifier: Development Status :: 5 - Production/Stable
Classifier: Intended Audience :: Developers
Classifier: Topic :: Software Development
Classifier: License :: OSI Approved :: MIT License
Classifier: Programming Language :: Python :: 3.11
Classifier: Programming Language :: Python :: 3.12
Classifier: Programming Language :: Python :: 3.13
License-File: LICENSE
Requires-Dist: matplotlib>=3.10.1
Dynamic: author
Dynamic: author-email
Dynamic: classifier
Dynamic: description
Dynamic: description-content-type
Dynamic: download-url
Dynamic: home-page
Dynamic: keywords
Dynamic: license
Dynamic: license-file
Dynamic: requires-dist
Dynamic: summary
